[{"id":"improvement-WpCdXiYH","date":"2018-07-20T08:30:05.283Z","caption":"We can make a better speedboats. We can have: rickety overloaded!","postedToGit":true,"htmlFragment":"<li class=\"pane\">\n  <div class=\"time-stamp entry-meta\">\n    <a href=\"improvement-WpCdXiYH.html\">\n      <time datetime=\"2018-07-20T08:30:05.283Z\">2018-7-20 04:30:05</time>\n    </a>\n  </div><div class=\"text-caption\">We can make a better speedboats. We can have: rickety overloaded!</div>\n</li>","postedSingleVideoPage":true},{"id":"improvement-kfuclrfv","date":"2018-07-20T11:30:04.598Z","caption":"CLANG CLANG CLANG! I am reforging \"Serapis\" into: heroic!","postedToGit":true,"htmlFragment":"<li class=\"pane\">\n  <div class=\"time-stamp entry-meta\">\n    <a href=\"improvement-kfuclrfv.html\">\n      <time datetime=\"2018-07-20T11:30:04.598Z\">2018-7-20 07:30:04</time>\n    </a>\n  </div><div class=\"text-caption\">CLANG CLANG CLANG! I am reforging \"Serapis\" into: heroic!</div>\n</li>","postedSingleVideoPage":true},{"id":"improvement-tSfoJxxq","date":"2018-07-20T14:30:04.509Z","caption":"We can make a better pronouncement. We can have: fundamental precept!","postedToGit":true,"htmlFragment":"<li class=\"pane\">\n  <div class=\"time-stamp entry-meta\">\n    <a href=\"improvement-tSfoJxxq.html\">\n      <time datetime=\"2018-07-20T14:30:04.509Z\">2018-7-20 10:30:04</time>\n    </a>\n  </div><div class=\"text-caption\">We can make a better pronouncement. We can have: fundamental precept!</div>\n</li>","postedSingleVideoPage":true},{"id":"improvement-HHTgpCzZ","date":"2018-07-20T17:30:04.363Z","caption":"We can make a better surefire. We can have: uncomplicated!","postedToGit":true,"htmlFragment":"<li class=\"pane\">\n  <div class=\"time-stamp entry-meta\">\n    <a href=\"improvement-HHTgpCzZ.html\">\n      <time datetime=\"2018-07-20T17:30:04.363Z\">2018-7-20 13:30:04</time>\n    </a>\n  </div><div class=\"text-caption\">We can make a better surefire. We can have: uncomplicated!</div>\n</li>","postedSingleVideoPage":true},{"id":"improvement-qZCYbbkV","date":"2018-07-20T20:30:05.450Z","caption":"We can make a better madeleine. We can have: dal chawal!","postedToGit":true,"htmlFragment":"<li class=\"pane\">\n  <div class=\"time-stamp entry-meta\">\n    <a href=\"improvement-qZCYbbkV.html\">\n      <time datetime=\"2018-07-20T20:30:05.450Z\">2018-7-20 16:30:05</time>\n    </a>\n  </div><div class=\"text-caption\">We can make a better madeleine. We can have: dal chawal!</div>\n</li>","postedSingleVideoPage":true},{"id":"improvement-BNxqRCjL","date":"2018-07-20T23:30:03.993Z","caption":"We can make a better warmers. We can have: repeller!","postedToGit":true,"htmlFragment":"<li class=\"pane\">\n  <div class=\"time-stamp entry-meta\">\n    <a href=\"improvement-BNxqRCjL.html\">\n      <time datetime=\"2018-07-20T23:30:03.993Z\">2018-7-20 19:30:03</time>\n    </a>\n  </div><div class=\"text-caption\">We can make a better warmers. We can have: repeller!</div>\n</li>","postedSingleVideoPage":true},{"id":"improvement-QvNkAbmW","date":"2018-07-21T02:30:05.762Z","caption":"Whirrr click! Whirrr click! \"Albertans\" has been reassembled into: preretirees!","postedToGit":true,"htmlFragment":"<li class=\"pane\">\n  <div class=\"time-stamp entry-meta\">\n    <a href=\"improvement-QvNkAbmW.html\">\n      <time datetime=\"2018-07-21T02:30:05.762Z\">2018-7-20 22:30:05</time>\n    </a>\n  </div><div class=\"text-caption\">Whirrr click! Whirrr click! \"Albertans\" has been reassembled into: preretirees!</div>\n</li>","postedSingleVideoPage":true},{"id":"improvement-USHcYBAf","date":"2018-07-21T05:30:04.678Z","caption":"We can make a better unfolding. We can have: shakier ground!","postedToGit":true,"htmlFragment":"<li class=\"pane\">\n  <div class=\"time-stamp entry-meta\">\n    <a href=\"improvement-USHcYBAf.html\">\n      <time datetime=\"2018-07-21T05:30:04.678Z\">2018-7-21 01:30:04</time>\n    </a>\n  </div><div class=\"text-caption\">We can make a better unfolding. We can have: shakier ground!</div>\n</li>","postedSingleVideoPage":true},{"id":"improvement-OXKFqvgJ","date":"2018-07-21T08:30:05.530Z","caption":"Whirrr click! Whirrr click! \"educations\" has been reassembled into: buppies!","postedToGit":true,"htmlFragment":"<li class=\"pane\">\n  <div class=\"time-stamp entry-meta\">\n    <a href=\"improvement-OXKFqvgJ.html\">\n      <time datetime=\"2018-07-21T08:30:05.530Z\">2018-7-21 04:30:05</time>\n    </a>\n  </div><div class=\"text-caption\">Whirrr click! Whirrr click! \"educations\" has been reassembled into: buppies!</div>\n</li>","postedSingleVideoPage":true},{"id":"improvement-EzodGdlI","date":"2018-07-21T11:30:03.833Z","caption":"I'm going to rebuild troika into something much better: sterner!","postedToGit":true,"htmlFragment":"<li class=\"pane\">\n  <div class=\"time-stamp entry-meta\">\n    <a href=\"improvement-EzodGdlI.html\">\n      <time datetime=\"2018-07-21T11:30:03.833Z\">2018-7-21 07:30:03</time>\n    </a>\n  </div><div class=\"text-caption\">I'm going to rebuild troika into something much better: sterner!</div>\n</li>","postedSingleVideoPage":true},{"id":"improvement-LhEUNGVV","date":"2018-07-21T14:30:05.111Z","caption":"OK! I'm improving \"embodiment\" for you! Now you have: harnessed!","postedToGit":true,"htmlFragment":"<li class=\"pane\">\n  <div class=\"time-stamp entry-meta\">\n    <a href=\"improvement-LhEUNGVV.html\">\n      <time datetime=\"2018-07-21T14:30:05.111Z\">2018-7-21 10:30:05</time>\n    </a>\n  </div><div class=\"text-caption\">OK! I'm improving \"embodiment\" for you! Now you have: harnessed!</div>\n</li>","postedSingleVideoPage":true},{"id":"improvement-PFbBwiDx","date":"2018-07-21T17:30:04.710Z","caption":"I'm going to rebuild detailing into something much better: surfaced!","postedToGit":true,"htmlFragment":"<li class=\"pane\">\n  <div class=\"time-stamp entry-meta\">\n    <a href=\"improvement-PFbBwiDx.html\">\n      <time datetime=\"2018-07-21T17:30:04.710Z\">2018-7-21 13:30:04</time>\n    </a>\n  </div><div class=\"text-caption\">I'm going to rebuild detailing into something much better: surfaced!</div>\n</li>","postedSingleVideoPage":true},{"id":"improvement-fKSetRBv","date":"2018-07-21T20:30:05.033Z","caption":"CLANG CLANG CLANG! I am reforging \"dysfunctions\" into: neuromusculoskeletal!","postedToGit":true,"htmlFragment":"<li class=\"pane\">\n  <div class=\"time-stamp entry-meta\">\n    <a href=\"improvement-fKSetRBv.html\">\n      <time datetime=\"2018-07-21T20:30:05.033Z\">2018-7-21 16:30:05</time>\n    </a>\n  </div><div class=\"text-caption\">CLANG CLANG CLANG! I am reforging \"dysfunctions\" into: neuromusculoskeletal!</div>\n</li>","postedSingleVideoPage":true},{"id":"improvement-nbVpHssZ","date":"2018-07-21T23:30:04.297Z","caption":"I'm going to rebuild skinner into something much better: cleanly zipped!","postedToGit":true,"htmlFragment":"<li class=\"pane\">\n  <div class=\"time-stamp entry-meta\">\n    <a href=\"improvement-nbVpHssZ.html\">\n      <time datetime=\"2018-07-21T23:30:04.297Z\">2018-7-21 19:30:04</time>\n    </a>\n  </div><div class=\"text-caption\">I'm going to rebuild skinner into something much better: cleanly zipped!</div>\n</li>","postedSingleVideoPage":true},{"id":"improvement-gprcvrGd","date":"2018-07-22T02:30:05.094Z","caption":"CLANG CLANG CLANG! I am reforging \"banks\" into: agriculturals!","postedToGit":true,"htmlFragment":"<li class=\"pane\">\n  <div class=\"time-stamp entry-meta\">\n    <a href=\"improvement-gprcvrGd.html\">\n      <time datetime=\"2018-07-22T02:30:05.094Z\">2018-7-21 22:30:05</time>\n    </a>\n  </div><div class=\"text-caption\">CLANG CLANG CLANG! I am reforging \"banks\" into: agriculturals!</div>\n</li>","postedSingleVideoPage":true},{"id":"improvement-PEoSXkcU","date":"2018-07-22T05:30:04.450Z","caption":"OK! I'm improving \"froze\" for you! Now you have: dinged!","postedToGit":true,"htmlFragment":"<li class=\"pane\">\n  <div class=\"time-stamp entry-meta\">\n    <a href=\"improvement-PEoSXkcU.html\">\n      <time datetime=\"2018-07-22T05:30:04.450Z\">2018-7-22 01:30:04</time>\n    </a>\n  </div><div class=\"text-caption\">OK! I'm improving \"froze\" for you! Now you have: dinged!</div>\n</li>","postedSingleVideoPage":true},{"id":"improvement-WuprISSQ","date":"2018-07-22T08:30:05.627Z","caption":"CLANG CLANG CLANG! I am reforging \"vileness\" into: unmitigated arrogance!","postedToGit":true,"htmlFragment":"<li class=\"pane\">\n  <div class=\"time-stamp entry-meta\">\n    <a href=\"improvement-WuprISSQ.html\">\n      <time datetime=\"2018-07-22T08:30:05.627Z\">2018-7-22 04:30:05</time>\n    </a>\n  </div><div class=\"text-caption\">CLANG CLANG CLANG! I am reforging \"vileness\" into: unmitigated arrogance!</div>\n</li>","postedSingleVideoPage":true},{"id":"improvement-uFcxyESZ","date":"2018-07-22T11:30:04.416Z","caption":"We can make a better portions. We can have: vast!","postedToGit":true,"htmlFragment":"<li class=\"pane\">\n  <div class=\"time-stamp entry-meta\">\n    <a href=\"improvement-uFcxyESZ.html\">\n      <time datetime=\"2018-07-22T11:30:04.416Z\">2018-7-22 07:30:04</time>\n    </a>\n  </div><div class=\"text-caption\">We can make a better portions. We can have: vast!</div>\n</li>","postedSingleVideoPage":true},{"id":"improvement-FZybezaR","date":"2018-07-22T14:30:05.618Z","caption":"We can make a better unreliability. We can have: lumbering bureaucracy!","postedToGit":true,"htmlFragment":"<li class=\"pane\">\n  <div class=\"time-stamp entry-meta\">\n    <a href=\"improvement-FZybezaR.html\">\n      <time datetime=\"2018-07-22T14:30:05.618Z\">2018-7-22 10:30:05</time>\n    </a>\n  </div><div class=\"text-caption\">We can make a better unreliability. We can have: lumbering bureaucracy!</div>\n</li>","postedSingleVideoPage":true},{"id":"improvement-tzyFUrpc","date":"2018-07-22T17:30:04.890Z","caption":"I'm going to rebuild centralization into something much better: prioritizations!","postedToGit":true,"htmlFragment":"<li class=\"pane\">\n  <div class=\"time-stamp entry-meta\">\n    <a href=\"improvement-tzyFUrpc.html\">\n      <time datetime=\"2018-07-22T17:30:04.890Z\">2018-7-22 13:30:04</time>\n    </a>\n  </div><div class=\"text-caption\">I'm going to rebuild centralization into something much better: prioritizations!</div>\n</li>","postedSingleVideoPage":true},{"id":"improvement-BciJypsa","date":"2018-07-22T20:30:04.964Z","caption":"I'm going to rebuild adjuncts into something much better: contractuals!","postedToGit":true,"htmlFragment":"<li class=\"pane\">\n  <div class=\"time-stamp entry-meta\">\n    <a href=\"improvement-BciJypsa.html\">\n      <time datetime=\"2018-07-22T20:30:04.964Z\">2018-7-22 16:30:04</time>\n    </a>\n  </div><div class=\"text-caption\">I'm going to rebuild adjuncts into something much better: contractuals!</div>\n</li>","postedSingleVideoPage":true},{"id":"improvement-CPawJXtE","date":"2018-07-22T23:30:04.353Z","caption":"I'm going to rebuild keyword into something much better: pageview!","postedToGit":true,"htmlFragment":"<li class=\"pane\">\n  <div class=\"time-stamp entry-meta\">\n    <a href=\"improvement-CPawJXtE.html\">\n      <time datetime=\"2018-07-22T23:30:04.353Z\">2018-7-22 19:30:04</time>\n    </a>\n  </div><div class=\"text-caption\">I'm going to rebuild keyword into something much better: pageview!</div>\n</li>","postedSingleVideoPage":true},{"id":"improvement-cJBwyqQg","date":"2018-07-23T02:30:05.489Z","caption":"We can make a better Missourians. We can have: statewide!","postedToGit":true,"htmlFragment":"<li class=\"pane\">\n  <div class=\"time-stamp entry-meta\">\n    <a href=\"improvement-cJBwyqQg.html\">\n      <time datetime=\"2018-07-23T02:30:05.489Z\">2018-7-22 22:30:05</time>\n    </a>\n  </div><div class=\"text-caption\">We can make a better Missourians. We can have: statewide!</div>\n</li>","postedSingleVideoPage":true}]