[{"id":"improvement-SrlHXMmQ","date":"2018-09-02T08:30:04.822Z","caption":"We can make a better grassland. We can have: pigweeds!","postedToGit":true,"htmlFragment":"<li class=\"pane\">\n  <div class=\"time-stamp entry-meta\">\n    <a href=\"improvement-SrlHXMmQ.html\">\n      <time datetime=\"2018-09-02T08:30:04.822Z\">2018-9-2 04:30:04</time>\n    </a>\n  </div><div class=\"text-caption\">We can make a better grassland. We can have: pigweeds!</div>\n</li>","postedSingleVideoPage":true},{"id":"improvement-kJSbMWLs","date":"2018-09-02T11:30:04.919Z","caption":"I'm going to rebuild photocopying into something much better: computerizing!","postedToGit":true,"htmlFragment":"<li class=\"pane\">\n  <div class=\"time-stamp entry-meta\">\n    <a href=\"improvement-kJSbMWLs.html\">\n      <time datetime=\"2018-09-02T11:30:04.919Z\">2018-9-2 07:30:04</time>\n    </a>\n  </div><div class=\"text-caption\">I'm going to rebuild photocopying into something much better: computerizing!</div>\n</li>","postedSingleVideoPage":true}]